minimal_honeycomb/__init__.py
minimal_honeycomb/core.py
wf_minimal_honeycomb_python-0.6.0.dist-info/LICENSE
wf_minimal_honeycomb_python-0.6.0.dist-info/METADATA
wf_minimal_honeycomb_python-0.6.0.dist-info/WHEEL
wf_minimal_honeycomb_python-0.6.0.dist-info/top_level.txt
wf_minimal_honeycomb_python-0.6.0.dist-info/RECORD
